soundcharts/__init__.py
soundcharts/album.py
soundcharts/api_util.py
soundcharts/artist.py
soundcharts/charts.py
soundcharts/client.py
soundcharts/festival.py
soundcharts/mylibrary.py
soundcharts/playlist.py
soundcharts/publisher.py
soundcharts/radio.py
soundcharts/referential.py
soundcharts/search.py
soundcharts/song.py
soundcharts/tiktok.py
soundcharts/user.py
soundcharts/venue.py
soundcharts/work.py
soundcharts-1.0.2.dist-info/licenses/LICENSE
soundcharts-1.0.2.dist-info/METADATA
soundcharts-1.0.2.dist-info/WHEEL
soundcharts-1.0.2.dist-info/top_level.txt
soundcharts-1.0.2.dist-info/RECORD
