Metadata-Version: 2.4
Name: soundcharts
Version: 1.0.2
Summary: A Python package for interacting with the Soundcharts API.
Author-email: Soundcharts Tech <tech@soundcharts.com>
License-Expression: GPL-3.0-only
Project-URL: Homepage, https://github.com/soundcharts/python-sdk
Project-URL: Issues, https://github.com/soundcharts/python-sdk/issues
Classifier: Programming Language :: Python :: 3
Classifier: Operating System :: OS Independent
Requires-Python: >=3.8
License-File: LICENSE
Requires-Dist: requests>=2.25.1
Requires-Dist: aiohttp
Dynamic: license-file
